alibabacloud_emr_serverless_spark20230808/__init__.py
alibabacloud_emr_serverless_spark20230808/client.py
alibabacloud_emr_serverless_spark20230808/models/__init__.py
alibabacloud_emr_serverless_spark20230808/models/_add_members_request.py
alibabacloud_emr_serverless_spark20230808/models/_add_members_response.py
alibabacloud_emr_serverless_spark20230808/models/_add_members_response_body.py
alibabacloud_emr_serverless_spark20230808/models/_artifact.py
alibabacloud_emr_serverless_spark20230808/models/_cancel_job_run_request.py
alibabacloud_emr_serverless_spark20230808/models/_cancel_job_run_response.py
alibabacloud_emr_serverless_spark20230808/models/_cancel_job_run_response_body.py
alibabacloud_emr_serverless_spark20230808/models/_cancel_kyuubi_spark_application_request.py
alibabacloud_emr_serverless_spark20230808/models/_cancel_kyuubi_spark_application_response.py
alibabacloud_emr_serverless_spark20230808/models/_cancel_kyuubi_spark_application_response_body.py
alibabacloud_emr_serverless_spark20230808/models/_category.py
alibabacloud_emr_serverless_spark20230808/models/_configuration.py
alibabacloud_emr_serverless_spark20230808/models/_configuration_overrides.py
alibabacloud_emr_serverless_spark20230808/models/_create_kyuubi_service_request.py
alibabacloud_emr_serverless_spark20230808/models/_create_kyuubi_service_response.py
alibabacloud_emr_serverless_spark20230808/models/_create_kyuubi_service_response_body.py
alibabacloud_emr_serverless_spark20230808/models/_create_kyuubi_token_request.py
alibabacloud_emr_serverless_spark20230808/models/_create_kyuubi_token_response.py
alibabacloud_emr_serverless_spark20230808/models/_create_kyuubi_token_response_body.py
alibabacloud_emr_serverless_spark20230808/models/_create_livy_compute_request.py
alibabacloud_emr_serverless_spark20230808/models/_create_livy_compute_response.py
alibabacloud_emr_serverless_spark20230808/models/_create_livy_compute_response_body.py
alibabacloud_emr_serverless_spark20230808-1.20.0.dist-info/LICENSE
alibabacloud_emr_serverless_spark20230808-1.20.0.dist-info/METADATA
alibabacloud_emr_serverless_spark20230808-1.20.0.dist-info/WHEEL
alibabacloud_emr_serverless_spark20230808-1.20.0.dist-info/top_level.txt
alibabacloud_emr_serverless_spark20230808-1.20.0.dist-info/RECORD
